ff_fun_demo.py
ff_fun_demo-0.0.0.3.dist-info/METADATA
ff_fun_demo-0.0.0.3.dist-info/WHEEL
ff_fun_demo-0.0.0.3.dist-info/top_level.txt
ff_fun_demo-0.0.0.3.dist-info/RECORD
