Metadata-Version: 2.1
Name: ff-fun-demo
Version: 0.0.0.3
Summary: special-purpose
Home-page: https://gitee.com/fanfan007/py_fun_demo.git
Author: 范范
Author-email: 516702882@qq.com
License: MIT
Platform: UNKNOWN
Requires: datetime
Requires: fake_useragent
Requires: sys
Requires: time
Requires: hashlib
Requires: urllib3
Requires: requests
Requires: aliyunsdkcore
Requires: random
